siftdb_client/__init__.py
siftdb_client/client.py
siftdb_client/models.py
siftdb-0.2.2.dist-info/METADATA
siftdb-0.2.2.dist-info/WHEEL
siftdb-0.2.2.dist-info/top_level.txt
siftdb-0.2.2.dist-info/RECORD
